[
    {
      "data": "2024-06-20",
      "evento": "live su twitch"
    },
    {
      "data": "2024-06-12",
      "evento": "inizio sviluppo del sito!"
    },
    {
      "data": "2024-07-04",
      "evento": "riunione del team"
    },
    {
      "data": "2024-07-14",
      "evento": "presentazione del progetto"
    },
    {
      "data": "2024-08-01",
      "evento": "lancio della versione beta"
    },
    {
      "data": "2024-08-15",
      "evento": "festa di metà agosto"
    },
    {
      "data": "2024-09-10",
      "evento": "analisi dei feedback"
    },
    {
      "data": "2024-09-21",
      "evento": "rilascio della versione stabile"
    },
    {
      "data": "2024-10-05",
      "evento": "workshop di aggiornamento"
    },
    {
      "data": "2024-10-18",
      "evento": "hackathon interno"
    },
    {
      "data": "2024-11-11",
      "evento": "webinar sulle nuove funzionalità"
    },
    {
      "data": "2024-11-25",
      "evento": "conferenza di settore"
    },
    {
      "data": "2024-12-01",
      "evento": "preparativi per il rilascio di fine anno"
    },
    {
      "data": "2024-12-24",
      "evento": "festa di Natale aziendale"
    },
    {
      "data": "2025-01-10",
      "evento": "riunione di pianificazione annuale"
    },
    {
      "data": "2025-01-25",
      "evento": "seminario di formazione"
    },
    {
      "data": "2025-02-14",
      "evento": "evento di San Valentino"
    },
    {
      "data": "2025-02-28",
      "evento": "scadenza per le proposte di miglioramento"
    },
    {
      "data": "2025-03-15",
      "evento": "workshop di sviluppo personale"
    },
    {
      "data": "2025-03-31",
      "evento": "rilascio della nuova versione"
    },
    {
      "data": "2025-04-22",
      "evento": "giornata della terra"
    },
    {
      "data": "2025-04-30",
      "evento": "festa di primavera"
    },
    {
      "data": "2025-05-05",
      "evento": "meeting di aggiornamento trimestrale"
    },
    {
      "data": "2025-05-20",
      "evento": "presentazione delle nuove funzionalità"
    }
  ]
  